{"is_source_file": true, "format": "Java", "description": "This Java source file defines a Spring Boot configuration class WebConfig, which enables Cross-Origin Resource Sharing (CORS) for specific local development origins, allowing the frontend (e.g., React, Vue) to communicate with the backend during development.", "external_files": ["org.springframework.context.annotation.Bean", "org.springframework.context.annotation.Configuration", "org.springframework.web.cors.CorsConfiguration", "org.springframework.web.cors.UrlBasedCorsConfigurationSource", "org.springframework.web.filter.CorsFilter", "java.util.List"], "external_methods": ["List.of"], "published": ["WebConfig"], "classes": [{"name": "WebConfig", "description": "Spring configuration class to set up CORS filter allowing specified origins for development."}], "methods": [{"name": "corsFilter", "description": "Creates and registers a CorsFilter bean that allows cross-origin requests from localhost and 127.0.0.1 on specified ports, with common HTTP methods and headers."}], "calls": ["org.springframework.web.cors.CorsConfiguration.setAllowedOrigins", "org.springframework.web.cors.CorsConfiguration.setAllowedMethods", "org.springframework.web.cors.CorsConfiguration.setAllowedHeaders", "org.springframework.web.cors.CorsConfiguration.setAllowCredentials", "org.springframework.web.cors.CorsConfiguration.setMaxAge", "UrlBasedCorsConfigurationSource.registerCorsConfiguration", "new CorsFilter"], "search-terms": ["CORS", "CorsFilter", "WebConfig", "allowed origins", "Cross-Origin"], "state": 2, "file_id": 12, "knowledge_revision": 49, "git_revision": "", "revision_history": [{"25": ""}, {"49": ""}], "hash": "907faac6843a53932a143c5986b75bc3", "format-version": 4, "code-base-name": "notes_backend", "filename": "notes_backend/src/main/java/com/example/notesbackend/config/WebConfig.java"}